bitcoin_toolkit/__init__.py
bitcoin_toolkit/engine.py
bitcoin_toolkit/node.py
bitcoin_toolkit/parser.py
bitcoin_toolkit/trace.py
models/__init__.py
models/address.py
models/bitcoin.py
models/block.py
models/output.py
models/transaction.py
bitcoin_toolkit-0.0.2.dist-info/LICENSE.txt
bitcoin_toolkit-0.0.2.dist-info/METADATA
bitcoin_toolkit-0.0.2.dist-info/WHEEL
bitcoin_toolkit-0.0.2.dist-info/top_level.txt
bitcoin_toolkit-0.0.2.dist-info/RECORD
