Metadata-Version: 2.1
Name: bitcoin-toolkit
Version: 0.0.2
Summary: bitcoin toolkit
Home-page: https://github.com/uncleguanghui/bitcoin_toolkit
Author: guanghui.zhang
Author-email: 415558663@qq.com
License: MIT
Keywords: toolkit,bitcoin,blockchain,block,analysis,
Platform: UNKNOWN
Classifier: Development Status :: 3 - Alpha
Classifier: Environment :: MacOS X
Classifier: License :: OSI Approved :: MIT License
Classifier: Natural Language :: Chinese (Simplified)
Classifier: Operating System :: MacOS
Classifier: Operating System :: POSIX :: Linux
Classifier: Programming Language :: Python :: 3 :: Only
Requires-Python: >=3
Requires-Dist: redis (>=3.2.1)
Requires-Dist: psutil (>=5.7.0)
Requires-Dist: blockchain-parser (>=0.1.4)
Requires-Dist: networkx (>=2.4)
Requires-Dist: matplotlib (>=3.0.3)
Requires-Dist: pygraphviz (>=1.5)
